myto/__init__.py
myto/cli.py
myto/base/adapter.py
myto/base/beforeRunner.py
myto/base/ctx.py
myto/base/order.py
myto/base/runner.py
myto/base/task.py
myto/base/when.py
myto/beforeRunners/waitForProcess.py
myto/beforeRunners/waitForWindow.py
myto/tasks/openAppTask.py
myto/utils/clsprop.py
myto/when/time.py
myto/when/timer.py
myto-0.1.0.dist-info/METADATA
myto-0.1.0.dist-info/WHEEL
myto-0.1.0.dist-info/entry_points.txt
myto-0.1.0.dist-info/licenses/LICENSE
myto-0.1.0.dist-info/RECORD
