Metadata-Version: 2.4
Name: myto
Version: 0.1.0
Summary: A flexible Python-based task automation framework for personal use cases
Project-URL: Homepage, https://github.com/ZackaryW/myto
Project-URL: Repository, https://github.com/ZackaryW/myto
Project-URL: Issues, https://github.com/ZackaryW/myto/issues
Author-email: ZackaryW <gitzackw@gmail.com>
License: MIT License
License-File: LICENSE
Keywords: automation,personal,scheduler,task,workflow
Classifier: Development Status :: 3 - Alpha
Classifier: Intended Audience :: End Users/Desktop
Classifier: License :: OSI Approved :: MIT License
Classifier: Operating System :: OS Independent
Classifier: Programming Language :: Python :: 3
Classifier: Programming Language :: Python :: 3.8
Classifier: Programming Language :: Python :: 3.9
Classifier: Programming Language :: Python :: 3.10
Classifier: Programming Language :: Python :: 3.11
Classifier: Programming Language :: Python :: 3.12
Classifier: Topic :: Office/Business :: Scheduling
Classifier: Topic :: System :: Systems Administration
Classifier: Topic :: Utilities
Requires-Python: >=3.8
Requires-Dist: click>=8.2.1
